unfazed_redis/backends/namespaceclient.py
unfazed_redis/schema/option.py
unfazed_redis-0.0.2.dist-info/METADATA
unfazed_redis-0.0.2.dist-info/WHEEL
unfazed_redis-0.0.2.dist-info/licenses/LICENSE
unfazed_redis-0.0.2.dist-info/RECORD
