Metadata-Version: 2.4
Name: unfazed-redis
Version: 0.0.2
Summary: Redis client for Unfazed
License-File: LICENSE
Requires-Python: >=3.12
Requires-Dist: pydantic>=2.10.6
Requires-Dist: redis<6.0.0,>=5.2.1
